ssb_hatch/__about__.py
ssb_hatch/__init__.py
ssb_hatch-0.0.1.dist-info/METADATA
ssb_hatch-0.0.1.dist-info/WHEEL
ssb_hatch-0.0.1.dist-info/licenses/LICENSE.txt
ssb_hatch-0.0.1.dist-info/RECORD
